plotter/__init__.py
plotter/axes.py
plotter/everything.py
plotter/graph.py
plotter/mathfunction.py
plotter/xrange.py
plotter_elunico-0.2.0.dist-info/LICENSE
plotter_elunico-0.2.0.dist-info/METADATA
plotter_elunico-0.2.0.dist-info/WHEEL
plotter_elunico-0.2.0.dist-info/top_level.txt
plotter_elunico-0.2.0.dist-info/RECORD
