Metadata-Version: 2.1
Name: plotter-elunico
Version: 0.2.0
Summary: WORK IN PROGRESS - A friendlier wrapper around matplotlib
Home-page: https://github.com/elunico/plotter
Author: Thomas Povinelli
Author-email: tompov227@gmail.com
Classifier: Programming Language :: Python :: 3
Classifier: License :: OSI Approved :: MIT License
Classifier: Operating System :: OS Independent
Requires-Python: >=3.12
License-File: LICENSE
